tinyupdi/tinyupdi.py
tinyupdi-1.5.1.dist-info/LICENSE
tinyupdi-1.5.1.dist-info/METADATA
tinyupdi-1.5.1.dist-info/WHEEL
tinyupdi-1.5.1.dist-info/entry_points.txt
tinyupdi-1.5.1.dist-info/top_level.txt
tinyupdi-1.5.1.dist-info/RECORD
