Metadata-Version: 2.1
Name: tinyupdi
Version: 1.5.1
Summary: Minimal UPDI Programming Tool for tinyAVR
Author-email: Stefan Wagner <wagiminator@web.de>
Maintainer-email: Stefan Wagner <wagiminator@web.de>
License: MIT License
Project-URL: Homepage, https://wagiminator.github.io/
Project-URL: Repository, https://github.com/wagiminator/MCU-Flash-Tools
Project-URL: Issues, https://github.com/wagiminator/MCU-Flash-Tools/issues
Keywords: ISP,AVR,Microchip,ATtiny,tinyAVR,UPDI,microcontroller
Classifier: Development Status :: 5 - Production/Stable
Classifier: Programming Language :: Python :: 3
Classifier: License :: OSI Approved :: MIT License
Classifier: Operating System :: OS Independent
Classifier: Intended Audience :: Developers
Classifier: Topic :: Software Development :: Embedded Systems
Requires-Python: >=3.8
License-File: LICENSE
Requires-Dist: pyserial
